owt/__init__.py
owt/api/__init__.py
owt/api/auth.py
owt/channel.py
owt/client.py
owt/codec.py
owt/common.py
owt/constants.py
owt/info.py
owt/log.py
owt/mediaformat.py
owt/participant.py
owt/portal_types.py
owt/publication.py
owt/quic.py
owt/quic_types.py
owt/sdputils.py
owt/signaling.py
owt/stream.py
owt/sub_types.py
owt/subscription.py
owt/transport.py
owt/utils.py
owt/webrtc.py
owt-0.1.9.dist-info/METADATA
owt-0.1.9.dist-info/WHEEL
owt-0.1.9.dist-info/RECORD
